patch_antenna/__init__.py
patch_antenna/designer.py
patch_antenna-0.1.0.dist-info/LICENSE
patch_antenna-0.1.0.dist-info/METADATA
patch_antenna-0.1.0.dist-info/WHEEL
patch_antenna-0.1.0.dist-info/top_level.txt
patch_antenna-0.1.0.dist-info/RECORD
