Metadata-Version: 2.1
Name: patch-antenna
Version: 0.1.0
Summary: A simple patch antenna design library
Home-page: https://github.com/bhanuchander210/patch_antenna.git
Author: Bhanuchander Udhayakumar
Author-email: bhanuchander210@gmail.com
License: MIT
Platform: UNKNOWN
License-File: LICENSE
Requires-Dist: scipy (==1.9.0)
Requires-Dist: gerber-writer (==0.3.4)
